soika_memory/__init__.py
soika_memory/client/__init__.py
soika_memory/client/main.py
soika_memory/client/project.py
soika_memory/client/utils.py
soika_memory/configs/__init__.py
soika_memory/configs/base.py
soika_memory/configs/enums.py
soika_memory/configs/prompts.py
soika_memory/configs/embeddings/__init__.py
soika_memory/configs/embeddings/base.py
soika_memory/configs/llms/__init__.py
soika_memory/configs/llms/base.py
soika_memory/configs/vector_stores/__init__.py
soika_memory/configs/vector_stores/azure_ai_search.py
soika_memory/configs/vector_stores/baidu.py
soika_memory/configs/vector_stores/chroma.py
soika_memory/configs/vector_stores/elasticsearch.py
soika_memory/configs/vector_stores/faiss.py
soika_memory/configs/vector_stores/langchain.py
soika_memory/configs/vector_stores/milvus.py
soika_memory/configs/vector_stores/mongodb.py
soika_memory/configs/vector_stores/opensearch.py
soika_memory/configs/vector_stores/pgvector.py
soika_memory/configs/vector_stores/pinecone.py
soika_memory/configs/vector_stores/qdrant.py
soika_memory/configs/vector_stores/redis.py
soika_memory/configs/vector_stores/supabase.py
soika_memory/configs/vector_stores/upstash_vector.py
soika_memory/configs/vector_stores/vertex_ai_vector_search.py
soika_memory/embeddings/__init__.py
soika_memory/embeddings/aws_bedrock.py
soika_memory/embeddings/azure_openai.py
soika_memory/embeddings/base.py
soika_memory/embeddings/configs.py
soika_memory/embeddings/gemini.py
soika_memory/embeddings/huggingface.py
soika_memory/embeddings/langchain.py
soika_memory/embeddings/lmstudio.py
soika_memory/embeddings/mock.py
soika_memory/embeddings/ollama.py
soika_memory/embeddings/openai.py
soika_memory/embeddings/soikastack.py
soika_memory/embeddings/together.py
soika_memory/embeddings/vertexai.py
soika_memory/graphs/__init__.py
soika_memory/graphs/configs.py
soika_memory/graphs/tools.py
soika_memory/graphs/utils.py
soika_memory/graphs/neptune/__init__.py
soika_memory/graphs/neptune/base.py
soika_memory-1.2.2.dist-info/METADATA
soika_memory-1.2.2.dist-info/WHEEL
soika_memory-1.2.2.dist-info/licenses/LICENSE
soika_memory-1.2.2.dist-info/RECORD
